Metadata-Version: 2.4
Name: adafruit-circuitpython-irremote
Version: 5.0.6
Summary: CircuitPython library for infrared transmit and receive.
Author-email: Adafruit Industries <circuitpython@adafruit.com>
License: MIT
Project-URL: Homepage, https://github.com/adafruit/Adafruit_CircuitPython_IRRemote
Keywords: adafruit,infrared,transmit,receive,tx,rx,ir,hardware,micropython,circuitpython
Classifier: Intended Audience :: Developers
Classifier: Topic :: Software Development :: Libraries
Classifier: Topic :: Software Development :: Embedded Systems
Classifier: Topic :: System :: Hardware
Classifier: License :: OSI Approved :: MIT License
Classifier: Programming Language :: Python :: 3
License-File: LICENSE
Provides-Extra: optional
Dynamic: license-file
